ioc_typing/__init__.py
ioc_typing/ioc_classifier.py
ioc_typing-0.1.0.dist-info/LICENSE
ioc_typing-0.1.0.dist-info/METADATA
ioc_typing-0.1.0.dist-info/WHEEL
ioc_typing-0.1.0.dist-info/top_level.txt
ioc_typing-0.1.0.dist-info/RECORD
