Metadata-Version: 2.1
Name: ioc-typing
Version: 0.1.0
Summary: A Python library for identifying and classifying Indicators of Compromise (IOCs)
Author-email: Jan Wychowaniak <43786923+janwychowaniak@users.noreply.github.com>
License: MIT License
Project-URL: Homepage, https://github.com/janwychowaniak/ioc-typing
Keywords: security,ioc,classifier,cyber-security
Classifier: Programming Language :: Python :: 3
Classifier: License :: OSI Approved :: MIT License
Classifier: Operating System :: OS Independent
Requires-Python: >=3.7
License-File: LICENSE
Provides-Extra: dev
Requires-Dist: pytest>=7.0; extra == "dev"
Requires-Dist: pytest-cov; extra == "dev"
Requires-Dist: black; extra == "dev"
Requires-Dist: flake8; extra == "dev"
Requires-Dist: isort; extra == "dev"
Requires-Dist: build; extra == "dev"
Requires-Dist: twine; extra == "dev"
Requires-Dist: tox; extra == "dev"
